<?xml version="1.0" encoding="utf-8" ?>
<dwsync>
<file name="WhatDontIKnowYet.html" server="access818997717.webspace-data.io//" local="132271589947575114" remote="132274772030000000" Dst="2" />
<file name="Superbowl.html" server="access818997717.webspace-data.io//" local="132268774935427691" remote="132274772040000000" Dst="2" />
<file name="recipe.html" server="access818997717.webspace-data.io//" local="132272945407307111" remote="132274772100000000" Dst="2" />
<file name="quotes.html" server="access818997717.webspace-data.io//" local="132274949000020530" remote="132275652450000000" Dst="2" />
<file name="MyStuff.html" server="access818997717.webspace-data.io//" local="132268273927326997" remote="132274772280000000" Dst="2" />
<file name="MyLetter.html" server="access818997717.webspace-data.io//" local="132274945071891797" remote="132275652480000000" Dst="2" />
<file name="music.html" server="access818997717.webspace-data.io//" local="132268776478771976" remote="132274772390000000" Dst="2" />
<file name="index.html" server="access818997717.webspace-data.io//" local="132268259077445219" remote="132274772490000000" Dst="2" />
<file name="comedian.html" server="access818997717.webspace-data.io//" local="132268776389893788" remote="132274772490000000" Dst="2" />
<file name="celebrity.html" server="access818997717.webspace-data.io//" local="132268776313435564" remote="132274772580000000" Dst="2" />
</dwsync>